JulianPy/__init__.py
JulianPy/julian.py
JulianPy-1.0.1.dist-info/LICENSE
JulianPy-1.0.1.dist-info/METADATA
JulianPy-1.0.1.dist-info/WHEEL
JulianPy-1.0.1.dist-info/top_level.txt
JulianPy-1.0.1.dist-info/RECORD
